README.txt
setup.cfg
setup.py
docs/HISTORY.txt
docs/INSTALL.txt
docs/LICENSE.GPL
docs/LICENSE.txt
easyshop/__init__.py
easyshop.order.egg-info/PKG-INFO
easyshop.order.egg-info/SOURCES.txt
easyshop.order.egg-info/dependency_links.txt
easyshop.order.egg-info/entry_points.txt
easyshop.order.egg-info/namespace_packages.txt
easyshop.order.egg-info/not-zip-safe
easyshop.order.egg-info/requires.txt
easyshop.order.egg-info/top_level.txt
easyshop/order/__init__.py
easyshop/order/configure.zcml
easyshop/order/profiles.zcml
easyshop/order/tests.py
easyshop/order/adapters/__init__.py
easyshop/order/adapters/configure.zcml
easyshop/order/adapters/item_management.py
easyshop/order/adapters/order_management.py
easyshop/order/adapters/prices.py
easyshop/order/browser/__init__.py
easyshop/order/browser/configure.zcml
easyshop/order/browser/mail_order_received.pt
easyshop/order/browser/mail_order_received.py
easyshop/order/browser/mail_order_received_old.pt
easyshop/order/browser/mail_order_sent.pt
easyshop/order/browser/mail_order_submitted.pt
easyshop/order/browser/my_orders.pt
easyshop/order/browser/my_orders.py
easyshop/order/browser/order_view.pt
easyshop/order/browser/order_view.py
easyshop/order/browser/orders.pt
easyshop/order/browser/orders.py
easyshop/order/content/__init__.py
easyshop/order/content/containers.py
easyshop/order/content/order.py
easyshop/order/content/order_item.py
easyshop/order/events/__init__.py
easyshop/order/events/order.py
easyshop/order/profiles/default/factorytool.xml
easyshop/order/profiles/default/types.xml
easyshop/order/profiles/default/workflows.xml
easyshop/order/profiles/default/types/Order.xml
easyshop/order/profiles/default/types/OrderItem.xml
easyshop/order/profiles/default/types/OrdersContainer.xml
easyshop/order/profiles/default/workflows/easyshop_order_workflow/definition.xml
easyshop/order/subscribers/__init__.py
easyshop/order/subscribers/configure.zcml
easyshop/order/subscribers/mailing.py